padpo/__init__.py
padpo/__main__.py
padpo/github.py
padpo/padpo.py
padpo/pofile.py
padpo/checkers/__init__.py
padpo/checkers/baseclass.py
padpo/checkers/empty.py
padpo/checkers/fuzzy.py
padpo/checkers/glossary.py
padpo/checkers/grammalecte.py
padpo/checkers/linelength.py
padpo/checkers/nbsp.py
padpo-0.12.0.dist-info/METADATA
padpo-0.12.0.dist-info/WHEEL
padpo-0.12.0.dist-info/entry_points.txt
padpo-0.12.0.dist-info/licenses/LICENSE
padpo-0.12.0.dist-info/RECORD
