Metadata-Version: 2.3
Name: padpo
Version: 0.12.0
Summary: Linter for gettext files
Project-URL: repository, https://github.com/AFPy/padpo
Project-URL: homepage, https://github.com/AFPy/padpo
Project-URL: documentation, https://github.com/AFPy/padpo
Author-email: Vincent Poulailleau <vpoulailleau@gmail.com>
License-Expression: BSD-3-Clause
License-File: LICENSE
Keywords: gettext,grammalecte,linter
Classifier: Operating System :: OS Independent
Classifier: Programming Language :: Python :: 3.9
Classifier: Programming Language :: Python :: 3.10
Classifier: Programming Language :: Python :: 3.11
Classifier: Programming Language :: Python :: 3.12
Classifier: Programming Language :: Python :: 3.13
Requires-Python: >=3.9
Requires-Dist: pygrammalecte>=1.4
Requires-Dist: requests>=2.20.0
Requires-Dist: simplelogging<0.12,>=0.10
